nationality/__init__.py
nationality/nationality.py
country_nationality-0.1.0.dist-info/LICENCE
country_nationality-0.1.0.dist-info/METADATA
country_nationality-0.1.0.dist-info/WHEEL
country_nationality-0.1.0.dist-info/top_level.txt
country_nationality-0.1.0.dist-info/RECORD
