Metadata-Version: 2.1
Name: country-nationality
Version: 0.1.0
Summary: A Python package to get nationality by country code
Home-page: UNKNOWN
Author: Anand MC
Author-email: anand.mc.ofcl@gmail.com
License: UNKNOWN
Platform: UNKNOWN
Classifier: Programming Language :: Python :: 3
Classifier: License :: OSI Approved :: MIT License
Classifier: Operating System :: OS Independent
Requires-Python: >=3.6
License-File: LICENCE
